{
  "version": 1,
  "meta": {
    "unit": "cm",
    "pxToWorld": 1,
    "createdAt": "2026-03-14T07:59:00.430Z",
    "source": "draw.html"
  },
  "walls": [
    {
      "id": "3f756abd-e2a7-43ec-9782-338623b78b62",
      "kind": "capital",
      "a": {
        "x": -552.7559689863012,
        "y": 344.9137842020857
      },
      "b": {
        "x": -552.7559689863012,
        "y": -379.92660550458714
      },
      "locked": true
    },
    {
      "id": "46ab659d-03aa-4e23-942f-772cc2dfeef7",
      "kind": "capital",
      "a": {
        "x": -552.7559689863012,
        "y": -379.92660550458714
      },
      "b": {
        "x": 554.2459397622205,
        "y": -379.92660550458714
      },
      "locked": true
    },
    {
      "id": "53cf516d-e6c4-402b-a0e9-7bf29c72e7a0",
      "kind": "capital",
      "a": {
        "x": 554.2459397622205,
        "y": -379.92660550458714
      },
      "b": {
        "x": 554.2459397622205,
        "y": 344.9137842020857
      },
      "locked": true
    },
    {
      "id": "90d1eb9e-56d8-45f3-a582-39be24f2b2d4",
      "kind": "capital",
      "a": {
        "x": 554.2459397622205,
        "y": 344.9137842020857
      },
      "b": {
        "x": -552.7559689863012,
        "y": 344.9137842020857
      },
      "locked": true
    },
    {
      "id": "a74cdb5f-0afb-430c-bcf5-9a1d9b649595",
      "kind": "capital",
      "a": {
        "x": -171.3394495412844,
        "y": -379.92660550458714
      },
      "b": {
        "x": -171.3394495412844,
        "y": 79.71012584441299
      },
      "locked": true
    },
    {
      "id": "4a14a691-d831-43cc-9699-a3931003ad47",
      "kind": "capital",
      "a": {
        "x": -171.3394495412844,
        "y": -260.73394495412845
      },
      "b": {
        "x": -552.7559689863012,
        "y": -260.73394495412845
      },
      "locked": true
    },
    {
      "id": "fe4e8537-b4cf-42dc-88cd-20e87a988fc4",
      "kind": "capital",
      "a": {
        "x": -168.35962166042498,
        "y": 344.9137842020857
      },
      "b": {
        "x": -168.35962166042498,
        "y": 224.23118129345255
      },
      "locked": true
    }
  ],
  "windows": [
    {
      "id": "afa975fa-c7d6-4391-be13-ba030aa2bef2",
      "kind": "balcony",
      "wallId": "4a14a691-d831-43cc-9699-a3931003ad47",
      "t": 0.6132812706637192,
      "w": 180
    },
    {
      "id": "42b320de-351f-4317-bde3-d7e0471e50d0",
      "kind": "std",
      "wallId": "46ab659d-03aa-4e23-942f-772cc2dfeef7",
      "t": 0.17227455365285352,
      "w": 330.75961597687603
    },
    {
      "id": "d908c580-d633-44bd-beba-50c4fc4bee59",
      "kind": "std",
      "wallId": "46ab659d-03aa-4e23-942f-772cc2dfeef7",
      "t": 0.5080753618808727,
      "w": 100
    },
    {
      "id": "5ff734ae-48f7-44cb-a283-17c7af3c6fe1",
      "kind": "std",
      "wallId": "46ab659d-03aa-4e23-942f-772cc2dfeef7",
      "t": 0.7779273364910092,
      "w": 100
    }
  ],
  "doors": [
    {
      "id": "a69d7160-d76e-4e28-ad5b-186e43c5a8d3",
      "kind": "entry",
      "wallId": "90d1eb9e-56d8-45f3-a582-39be24f2b2d4",
      "t": 0.5262449485748808,
      "w": 90,
      "locked": true
    }
  ],
  "furniture": [
    {
      "id": "f075ca26-ce2e-41da-8ada-f247bff62cbc",
      "typeId": "stoyak",
      "symbolId": "mebel-stoyak",
      "w": 50,
      "h": 28,
      "x": 153.46048225612813,
      "y": 344.16878460525373,
      "rot": 0,
      "locked": true
    },
    {
      "id": "a67f27b0-9c89-46c2-8a68-a93a4f910523",
      "typeId": "stoyak-vertical",
      "symbolId": "mebel-stoyak-vertical",
      "w": 28,
      "h": 50,
      "x": -173.57433466080133,
      "y": -14.153997718741039,
      "rot": 0,
      "locked": true
    }
  ]
}